timestring/Date.py
timestring/Range.py
timestring/__init__.py
timestring/text2num.py
timestring/timestring_re.py
timestring-1.6.3.dist-info/LICENSE
timestring-1.6.3.dist-info/METADATA
timestring-1.6.3.dist-info/WHEEL
timestring-1.6.3.dist-info/entry_points.txt
timestring-1.6.3.dist-info/top_level.txt
timestring-1.6.3.dist-info/zip-safe
timestring-1.6.3.dist-info/RECORD
